thermoml_fair/Code Citations.md
thermoml_fair/__init__.py
thermoml_fair/__pycache__/__init__.cpython-313.pyc
thermoml_fair/core/__init__.py
thermoml_fair/core/chemistry_utils.py
thermoml_fair/core/config.py
thermoml_fair/core/extract.py
thermoml_fair/core/parser.py
thermoml_fair/core/schema.py
thermoml_fair/core/update_archive.py
thermoml_fair/core/utils.py
thermoml_fair/core/__pycache__/__init__.cpython-313.pyc
thermoml_fair/core/__pycache__/chemistry_utils.cpython-313.pyc
thermoml_fair/core/__pycache__/config.cpython-313.pyc
thermoml_fair/core/__pycache__/parser.cpython-313.pyc
thermoml_fair/core/__pycache__/schema.cpython-313.pyc
thermoml_fair/core/__pycache__/update_archive.cpython-313.pyc
thermoml_fair/core/__pycache__/utils.cpython-313.pyc
thermoml_fair/data/ThermoML.xsd
thermoml_fair/scripts/__init__.py
thermoml_fair/scripts/cli.py
thermoml_fair/scripts/update_archive.py
thermoml_fair/scripts/__pycache__/__init__.cpython-313.pyc
thermoml_fair/scripts/__pycache__/cli.cpython-313.pyc
thermoml_fair-1.0.25.dist-info/licenses/LICENSE
thermoml_fair-1.0.25.dist-info/METADATA
thermoml_fair-1.0.25.dist-info/WHEEL
thermoml_fair-1.0.25.dist-info/entry_points.txt
thermoml_fair-1.0.25.dist-info/top_level.txt
thermoml_fair-1.0.25.dist-info/RECORD
