Metadata-Version: 2.4
Name: thermoml_fair
Version: 1.0.25
Summary: Parser and data utilities for ThermoML datasets
Author-email: "Angela C. Davis" <angela.cf.davis@gmail.com>
License-Expression: GPL-3.0-or-later
Classifier: Programming Language :: Python :: 3
Classifier: Operating System :: OS Independent
Requires-Python: >=3.8
License-File: LICENSE
Requires-Dist: typer[all]
Requires-Dist: xmlschema>=1.11.0
Requires-Dist: pandas
Requires-Dist: numpy
Requires-Dist: requests
Requires-Dist: xmltodict
Requires-Dist: pymatgen
Requires-Dist: charset-normalizer
Requires-Dist: chardet
Provides-Extra: parquet
Requires-Dist: pyarrow; extra == "parquet"
Requires-Dist: fastparquet; extra == "parquet"
Dynamic: license-file
